{"word":"ரிப்லா (Riblah)","slug":"ரிப்லா","sections":[{"paragraph":"<strong>ஆங்கில பொருள்: </strong><br/>bare place, to be fruitful, ferti(lity)le, the strife ended, quarrel."},{"paragraph":"(WH7247)"},{"paragraph":"<strong>தமிழ் பொருள்: </strong><br/>வெறுமையான இடம், கனிகொடுப்பதாயிரு. செழிப்(பு)பான, தகராறு முடிந்தது, சண்டை, சச்சரவு."},{"paragraph":"<p><strong>விளக்கம்: </strong><p>"},{"paragraph":"1. கானான் தேசத்தின் (அல்லது 9.5ஒன்பதரைக் கோத்திரங்களுக்கு பங்கிடவேண்டிய தேசத்தின்) கீழ்ப்புற எல்லையிருந்த பட்டணம். (<a href=\"https://www.wordofgod.in/bibles/?book=4&chapter=34&verse=11\">எண் 34:11</a>) இதின் உண்மையான பெயர் (Harbel)\"அர்பேல்\". பாகாலின் அனேகம்(the Mount of Bel or Baal) தொழுகையிடங்களில் ஒன்று. பாகால் வழிபாட்டுத்தலத்தின் சிதைவுகளை இன்றும் அங்கே காணமுடியும்."},{"paragraph":"2. ஆமாத் தேச(த்தின் பட்டண)மான இதிலே எகிப்தின் ராஜாவாகிய பார்வோன்நேகோ யோவாகாஸ் என்னும் யூதாவின் 17பதினேழாவது ராஜாவைப் பிடித்துக் கட்டி எகிப்துக்குக் கொண்டுபோனான். (<a href=\"https://www.wordofgod.in/bibles/?book=12&chapter=23&verse=33\">2ராஜா 23:33</a>) பாபிலோன் ராஜா, சிதேக்கியா ராஜாவின் குமாரரை அவன் கண்களுக்கு முன்பாக வெட்டியதும், ராஜாவின் கண்களைக் குருடாக்கியதும் இப்பட்டணத்தில்தான். (<a href=\"https://www.wordofgod.in/bibles/?book=12&chapter=25&verse=6\">2ராஜா 25:6</a>; <a href=\"https://www.wordofgod.in/bibles/?book=24&chapter=39&verse=5\">எரே 39:5</a>; <a href=\"https://www.wordofgod.in/bibles/?book=24&chapter=39&verse=6\">எரே 39:6</a>; <a href=\"https://www.wordofgod.in/bibles/?book=24&chapter=52&verse=9\">எரே 52:9</a>; <a href=\"https://www.wordofgod.in/bibles/?book=24&chapter=52&verse=10\">எரே 52:10</a>) பிரதான ஆசாரியன், 2இரண்டாம் ஆசாரியன் முதலானோர் வெட்டிக் கொல்லப்பட்டதும் இங்கேதான். (<a href=\"https://www.wordofgod.in/bibles/?book=12&chapter=25&verse=20\">2ராஜா 25:20</a>; <a href=\"https://www.wordofgod.in/bibles/?book=12&chapter=25&verse=21\">2ராஜா 25:21</a>; <a href=\"https://www.wordofgod.in/bibles/?book=24&chapter=52&verse=26\">எரே 52:26</a>; <a href=\"https://www.wordofgod.in/bibles/?book=24&chapter=52&verse=27\">எரே 52:27</a>) <a href=\"https://wordofgod.in/bibledictionary/பரிபூரண-பெயர்ப்-பொக்கிஷம்/index.php?word=[ஆமாத்தேசம்\">[ஆமாத்தேசம்</a> காண்க]. 40நாற்பது 50ஐம்பது வீடுகளுடனே (Orontes) \"ஒரோன்டெஸ்\" ஆற்றின் வலதுபுறமான சமவெளியில் காணப்படும் இதின் தற்காலப் பெயர் (Ribleh)\"ரிப்லே\" ஆகும்."}]}