{"word":"G2386 - ἴαμα - íama - ee'-am-ah - Healing","slug":"G2386","sections":[{"paragraph":""},{"paragraph":"<strong>Original: </strong><span class=\"hebrewOrGreek\">ἴαμα</span>"},{"paragraph":"<strong>Transliteration: </strong>íama"},{"paragraph":"<strong>Phonetic: </strong>ee'-am-ah"},{"paragraph":"<strong>Short Definition: </strong>Healing"},{"paragraph":""},{"paragraph":"- Original: <b><el>ἴαμα</el></b> <p />- Transliteration: <b>Iama</b> <p />- Phonetic: <b>ee'-am-ah</b> <p class=\"def\">- Definition: </p> <p class='li260'><b>1.</b> a means of healing, remedy, medicine </p> <p class='li260'><b>2.</b> a healing </p> <p class=\"origin\"/>- Origin: from <a href=\"#/G2390\">G2390</a> <p />- TDNT entry: 06:14,3 <p />- Part(s) of speech: Noun Neuter <p />- Strong's: From <a href=\"#/G2390\">G2390</a>; a <i>cure</i> (the effect): - healing. "},{"paragraph":""},{"paragraph":"<strong>Cognate:</strong> <a href=\"#/G2390\">G2390</a>, <a href=\"#/G2392\">G2392</a>, <a href=\"#/G2395\">G2395</a>"}]}