{"word":"G2417 - ἱερόσυλος - hierósylos - hee-er-os'-oo-los - Robber of churches","slug":"G2417","sections":[{"paragraph":""},{"paragraph":"<strong>Original: </strong><span class=\"hebrewOrGreek\">ἱερόσυλος</span>"},{"paragraph":"<strong>Transliteration: </strong>hierósylos"},{"paragraph":"<strong>Phonetic: </strong>hee-er-os'-oo-los"},{"paragraph":"<strong>Short Definition: </strong>Robber of churches"},{"paragraph":""},{"paragraph":"- Original: <b><el>ἱερόσυλος</el></b> <p />- Transliteration: <b>Hierosulos</b> <p />- Phonetic: <b>hee-er-os'-oo-los</b> <p class=\"def\">- Definition: </p> <p class='li260'><b>1.</b> guilty of sacrilege </p> <p class=\"origin\"/>- Origin: from <a href=\"#/G2411\">G2411</a> and <a href=\"#/G4813\">G4813</a> <p />- TDNT entry: 07:16,3 <p />- Part(s) of speech: Noun Masculine <p />- Strong's: From <a href=\"#/G2411\">G2411</a> and <a href=\"#/G4813\">G4813</a>; a <i>temple</i> <b><i>despoiler</i></b>: - robber of churches. "},{"paragraph":""},{"paragraph":"<strong>Cognate:</strong> <a href=\"#/G1494\">G1494</a>, <a href=\"#/G2405\">G2405</a>, <a href=\"#/G2406\">G2406</a>, <a href=\"#/G2407\">G2407</a>, <a href=\"#/G2409\">G2409</a>, <a href=\"#/G2411\">G2411</a>, <a href=\"#/G2412\">G2412</a>, <a href=\"#/G2413\">G2413</a>, <a href=\"#/G2416\">G2416</a>, <a href=\"#/G2418\">G2418</a>, <a href=\"#/G2420\">G2420</a>, <a href=\"#/G749\">G749</a>"}]}