{"word":"G3314 - μεσημβρία - mesēmbría - mes-ame-bree'-ah - Noon","slug":"G3314","sections":[{"paragraph":""},{"paragraph":"<strong>Original: </strong><span class=\"hebrewOrGreek\">μεσημβρία</span>"},{"paragraph":"<strong>Transliteration: </strong>mesēmbría"},{"paragraph":"<strong>Phonetic: </strong>mes-ame-bree'-ah"},{"paragraph":"<strong>Short Definition: </strong>Noon"},{"paragraph":""},{"paragraph":"- Original: <b><el>μεσημβρία</el></b> <p />- Transliteration: <b>mesembria</b> <p />- Phonetic: <b>mes-ame-bree'-ah</b> <p class=\"def\">- Definition: </p> <p class='li260'><b>1.</b> as respects to time: noon </p> <p class='li260'><b>2.</b> as respects to locality </p> <p class='li520'><b>a.</b> the south </p> <p class=\"origin\"/>- Origin: from <a href=\"#/G3319\">G3319</a> and <a href=\"#/G2250\">G2250</a> <p />- TDNT entry: None <p />- Part(s) of speech: Noun Feminine <p />- Strong's: From <a href=\"#/G3319\">G3319</a> and <a href=\"#/G2250\">G2250</a>; <i>midday</i>; by implication the <b><i>south</i></b>: - noon south. "}]}