{"word":"G3523 - νῆστις - nēstis - nace'-tis - Fasting","slug":"G3523","sections":[{"paragraph":""},{"paragraph":"<strong>Original: </strong><span class=\"hebrewOrGreek\">νῆστις</span>"},{"paragraph":"<strong>Transliteration: </strong>nēstis"},{"paragraph":"<strong>Phonetic: </strong>nace'-tis"},{"paragraph":"<strong>Short Definition: </strong>Fasting"},{"paragraph":""},{"paragraph":"- Original: <b><el>νῆστις</el></b> <p />- Transliteration: <b>Nestis</b> <p />- Phonetic: <b>nace'-tis</b> <p class=\"def\">- Definition: </p> <p class='li260'><b>1.</b> fasting, not having eaten </p> <p class=\"origin\"/>- Origin: from the insep. negative particle ne- (not) and <a href=\"#/G2068\">G2068</a> <p />- TDNT entry: 19:24,6 <p />- Part(s) of speech: Noun Feminine <p />- Strong's: From the negative particle <el>νη</el> nē and <a href=\"#/G2068\">G2068</a>; <i>not eating</i> that is <i>abstinent</i> from food (religiously): - fasting."},{"paragraph":""},{"paragraph":"<strong>Cognate:</strong> <a href=\"#/G3521\">G3521</a>, <a href=\"#/G3522\">G3522</a>"}]}