{"word":"H3074 - יְהֹוָה שָׁמָּה - Yᵉhôvâh shâmmâh - yeh-ho-vaw' shawm'-maw - Jehovahshammah","slug":"H3074","sections":[{"paragraph":""},{"paragraph":"<strong>Original: </strong><span class=\"hebrewOrGreek\">יְהֹוָה שָׁמָּה</span>"},{"paragraph":"<strong>Transliteration: </strong>Yᵉhôvâh shâmmâh"},{"paragraph":"<strong>Phonetic: </strong>yeh-ho-vaw' shawm'-maw"},{"paragraph":"<strong>Short Definition: </strong>Jehovahshammah"},{"paragraph":""},{"paragraph":"Original: <b><he>יהוה שׁמּה</he></b> <p />Transliteration: <b>yehôvâh shâmmâh</b> <p />Phonetic: <b>yeh-ho-vaw' shawm'-maw</b> <p class=\"bdb_def\"><b>BDB Definition</b>:</p> Jehovah-shammah = \"Jehovah is there\" <ol><li>a symbolic name for Jerusalem</li></ol> <p />Origin: from <a href=\"#/H3068\">H3068</a> and <a href=\"#/H8033\">H8033</a> with directive enclitic <p />TWOT entry: None <p />Part(s) of speech: Proper Name Location "},{"paragraph":""},{"paragraph":"<strong>Cognate:</strong> <a href=\"#/H8033\">H8033</a>, <a href=\"#/H8034\">H8034</a>, <a href=\"#/H8035\">H8035</a>, <a href=\"#/H8038\">H8038</a>, <a href=\"#/H8050\">H8050</a>, <a href=\"#/H8061\">H8061</a>, <a href=\"#/H8062\">H8062</a>, <a href=\"#/H8070\">H8070</a>"}]}