{"word":"H46 - אָבִיר - ʼâbîyr - aw-beer' - Mighty","slug":"H46","sections":[{"paragraph":""},{"paragraph":"<strong>Original: </strong><span class=\"hebrewOrGreek\">אָבִיר</span>"},{"paragraph":"<strong>Transliteration: </strong>ʼâbîyr"},{"paragraph":"<strong>Phonetic: </strong>aw-beer'"},{"paragraph":"<strong>Short Definition: </strong>Mighty"},{"paragraph":""},{"paragraph":"Original: <b><he>אביר</he></b> <p />Transliteration: <b>'âbı̂yr</b> <p />Phonetic: <b>aw-beer'</b> <p class=\"bdb_def\"><b>BDB Definition</b>:</p><ol><li>strong, mighty - used only to describe God</li><li>the Strong - old name for God (poetic)</li></ol> <p />Origin: from <a href=\"#/H82\">H82</a> <p />TWOT entry: <a class=\"T\" href=\"S:0013 - 'br\">13c</a> <p />Part(s) of speech: Adjective Masculine "},{"paragraph":""},{"paragraph":"<strong>Cognate:</strong> <a href=\"#/H47\">H47</a>, <a href=\"#/H82\">H82</a>, <a href=\"#/H83\">H83</a>, <a href=\"#/H84\">H84</a>"}]}