{"word":"H7577 - רְתֻקָה - rᵉthuqâh - reth-oo-kaw' - Chain","slug":"H7577","sections":[{"paragraph":""},{"paragraph":"<strong>Original: </strong><span class=\"hebrewOrGreek\">רְתֻקָה</span>"},{"paragraph":"<strong>Transliteration: </strong>rᵉthuqâh"},{"paragraph":"<strong>Phonetic: </strong>reth-oo-kaw'"},{"paragraph":"<strong>Short Definition: </strong>Chain"},{"paragraph":""},{"paragraph":"Original: <b><he>רתקה</he></b> <p />Transliteration: <b>rethûqâh</b> <p />Phonetic: <b>reth-oo-kaw'</b> <p class=\"bdb_def\"><b>BDB Definition</b>:</p><ol><li>chain</li></ol> <p />Origin: pass part of <a href=\"#/H7576\">H7576</a> <p />TWOT entry: <a class=\"T\" href=\"S:2227 - rataq\">2227a</a> <p />Part(s) of speech: Noun Feminine "},{"paragraph":""},{"paragraph":"<strong>Cognate:</strong> <a href=\"#/H7569\">H7569</a>, <a href=\"#/H7572\">H7572</a>, <a href=\"#/H7576\">H7576</a>"}]}