{"word":"H7683 - שָׁגַג - shâgag - shaw-gag' - [idiom] also for that","slug":"H7683","sections":[{"paragraph":""},{"paragraph":"<strong>Original: </strong><span class=\"hebrewOrGreek\">שָׁגַג</span>"},{"paragraph":"<strong>Transliteration: </strong>shâgag"},{"paragraph":"<strong>Phonetic: </strong>shaw-gag'"},{"paragraph":"<strong>Short Definition: </strong>[idiom] also for that"},{"paragraph":""},{"paragraph":"Original: <b><he>שׁגג</he></b> <p />Transliteration: <b>shâgag</b> <p />Phonetic: <b>shaw-gag'</b> <p class=\"bdb_def\"><b>BDB Definition</b>:</p><ol><li>to go astray, err, commit sin or error<ol type='a'><li>(Qal)<ol><li>to err (mentally)</li><li>to sin (ignorantly or inadvertently)</li></ol></li></ol></li></ol> <p />Origin: a primitive root <p />TWOT entry: <a class=\"T\" href=\"S:2324 - shagag\">2324</a> <p />Part(s) of speech: Verb "},{"paragraph":""},{"paragraph":"<strong>Cognate:</strong> <a href=\"#/H7684\">H7684</a>"}]}