{"word":"μαραίνω","slug":"μαραίνω","sections":[{"paragraph":""},{"paragraph":""},{"paragraph":"<p ><strong><elT>μαραίνω</elT></strong> <a href=\"#_ftn1\" name=\"_ftnref1\">aor.</a> 3 <a href=\"#_ftn2\" name=\"_ftnref2\">pl.</a> <a href=\"#_ftn3\" name=\"_ftnref3\">ptc.</a> <el>ἐμάραναν</el> <a class='B' href='B:270 19:21'>Wsd 19:21</a>, <a href=\"#_ftn4\" name=\"_ftnref4\">opt.</a> 3 <a href=\"#_ftn5\" name=\"_ftnref5\">sg.</a> <el>μαράναι</el> <a class='B' href='B:220 15:30'>Job 15:30</a>. Pass.: 1fut. <el>μαρανθήσομαι</el>; 1 aor. <el>ἐμαράνθην</el>; <a href=\"#_ftn6\" name=\"_ftnref6\">pf.</a> ptc. <el>μεμαραμμένος</el> (<a href=\"#_ftn7\" name=\"_ftnref7\">B-D-F</a> §72) (<a href=\"#_ftn8\" name=\"_ftnref8\">Hom</a>. <a href=\"#_ftn9\" name=\"_ftnref9\">et al.</a>; <a href=\"#_ftn10\" name=\"_ftnref10\">ins</a>, <a href=\"#_ftn11\" name=\"_ftnref11\">pap</a>, <a href=\"#_ftn12\" name=\"_ftnref12\">LXX</a>; <a href=\"#_ftn13\" name=\"_ftnref13\">gener.</a> ‘quench, destroy’) in our <a href=\"#_ftn14\" name=\"_ftnref14\">lit.</a> only <a href=\"#_ftn15\" name=\"_ftnref15\">pass.</a> in <a href=\"#_ftn16\" name=\"_ftnref16\">act.</a> sense: <strong>to disappear gradually</strong>, <strong><em>die out, fade, disappear, wither</em></strong> of plants (<a href=\"#_ftn17\" name=\"_ftnref17\">schol.</a> on <a href=\"#_ftn18\" name=\"_ftnref18\">Nicander</a>, Ther. 677; <a class='B' href='B:220 15:30'>Job 15:30</a>; <a class='B' href='B:270 2:8'>Wsd 2:8</a>) <el>ὡς μεμαραμμέναι</el> <em>as if withered</em> <a href=\"#_ftn19\" name=\"_ftnref19\">Hs</a> 9, 1, 7; <a href=\"#_ftn20\" name=\"_ftnref20\">cp.</a> 9, 23, 1f. Of one’s spirit <a href=\"#_ftn21\" name=\"_ftnref21\">v</a> 3, 11, 2 (cp. <a href=\"#_ftn22\" name=\"_ftnref22\">Appian</a>, Bell. Civ. 5, 90 §379 <el>μαραίνεσθαι</el> of the <el>πνεῦμα</el>, wind=abate fully, die down; <a href=\"#_ftn23\" name=\"_ftnref23\">Jos.</a>, Ant. 11, 56; <a href=\"#_ftn24\" name=\"_ftnref24\">ApcSed</a> 7:6 of beauty). Of Mary’s name <el>τὸ ὄνομα αὐτῆς οὐ μαρανθήσεται εἰς τὸν αἰῶνα</el> <a href=\"#_ftn25\" name=\"_ftnref25\">GJs</a> 6:3 (codd. not Bodmer). Of <a href=\"#_ftn26\" name=\"_ftnref26\">pers.</a> (<a href=\"#_ftn27\" name=\"_ftnref27\">Aristaen</a>., <a href=\"#_ftn28\" name=\"_ftnref28\">Ep.</a> 1, 10 <el>μαραινόμενος τ</el>. <el>νοῦν</el>), in gnomic statement: <el>ὁ πλούσιος ἐν ταῖς πορείαις … μαρανθήσεται</el> <em>a rich person will wither away while trafficking</em> <strong><a class='B' href='B:660 1:11'>Js 1:11</a></strong> (s. the grave-inscription <a href=\"#_ftn29\" name=\"_ftnref29\">Sb</a> 5199, 2 <el>ἐμαράνθη</el>; Jos., Bell. 6, 274 <el>λιμῷ μαραινόμενοι</el>; <a href=\"#_ftn30\" name=\"_ftnref30\">TestSim</a> 3:3).—<strong><a class='B' href='B:470 5:13'>Mt 5:13</a></strong> <a href=\"#_ftn31\" name=\"_ftnref31\">v.l.</a>; <strong><a class='B' href='B:490 14:34'>Lk 14:34</a></strong> v.l. (both for <el>μωρανθῇ</el>).—<a href=\"#_ftn32\" name=\"_ftnref32\">BHHW</a> II 1144. <a href=\"#_ftn33\" name=\"_ftnref33\">DELG</a>. <a href=\"#_ftn34\" name=\"_ftnref34\">M-M</a>. <a href=\"#_ftn35\" name=\"_ftnref35\">TW</a>. <a href=\"#_ftn36\" name=\"_ftnref36\">Spicq</a>.</p> <p ><a href=\"#_ftn37\" name=\"_ftnref37\"></a></p> <p ><a href=\"#_ftnref1\" name=\"_ftn1\">aor. </a><strong>aor.</strong> = aorist</p> <ol> <li><a href=\"#_ftnref2\" name=\"_ftn2\"> </a><strong>pl.</strong> = plural</li> </ol> <p ><a href=\"#_ftnref3\" name=\"_ftn3\">ptc. </a><strong>ptc.</strong> = participle</p> <p ><a href=\"#_ftnref4\" name=\"_ftn4\">opt. </a><strong>opt.</strong> = optative</p> <ol> <li><a href=\"#_ftnref5\" name=\"_ftn5\"> </a><strong>sg.</strong> = singular</li> <li><a href=\"#_ftnref6\" name=\"_ftn6\"> </a><strong>pf.</strong> = perfect</li> </ol> <p ><a href=\"#_ftnref7\" name=\"_ftn7\">B-D-F </a><strong>B-D-F</strong> = FBlass, ADebrunner, RFunk, A Greek Grammar of the New Testament and Other Early Christian Literature—List 6</p> <p ><a href=\"#_ftnref8\" name=\"_ftn8\">Hom </a><strong>Hom</strong> , VIII b.c.—List 5</p> <p ><a href=\"#_ftnref9\" name=\"_ftn9\">et al. </a><strong>et al.</strong> = et alii (and others)</p> <p ><a href=\"#_ftnref10\" name=\"_ftn10\">ins </a><strong>Ins, ins</strong> = Inscription, Inschrift, inscription(s). Without a period, esp. in lists, as at the beginning of entries; the capitalized form is used in titles. In conjunction with literary works this abbr. refers to the title or description of contents.</p> <p ><a href=\"#_ftnref11\" name=\"_ftn11\">pap </a><strong>pap</strong> = papyrus, -yri</p> <p ><a href=\"#_ftnref12\" name=\"_ftn12\">LXX </a><strong>LXX</strong> = Septuaginta, ed. ARahlfs, unless otherwise specified—Lists 2, beg.</p> <p ><a href=\"#_ftnref13\" name=\"_ftn13\">gener. </a><strong>gener.</strong> = generally</p> <p ><a href=\"#_ftnref14\" name=\"_ftn14\">lit. </a><strong>lit.</strong> = literal(ly); literature (refererences to [scholarly] literature)</p> <p ><a href=\"#_ftnref15\" name=\"_ftn15\">pass. </a><strong>pass.</strong> = passive (either of grammatical form or of passive experience); also used in reference to literary portion=passage</p> <p ><a href=\"#_ftnref16\" name=\"_ftn16\">act. </a><strong>act.</strong> = active</p> <p ><a href=\"#_ftnref17\" name=\"_ftn17\">schol. </a><strong>schol.</strong> = scholion, scholia, scholiast</p> <p ><a href=\"#_ftnref18\" name=\"_ftn18\">Nicander </a><strong>Nicander</strong> , III/II b.c.—List 5</p> <p ><a href=\"#_ftnref19\" name=\"_ftn19\">Hs </a><strong>Hs</strong> = Similitudes</p> <ol> <li><a href=\"#_ftnref20\" name=\"_ftn20\"> </a><strong>cp.</strong> = compare, freq. in ref. to citation fr. ancient texts</li> </ol> <p ><a href=\"#_ftnref21\" name=\"_ftn21\">v </a><strong>v</strong> = Visions</p> <p ><a href=\"#_ftnref22\" name=\"_ftn22\">Appian </a><strong>Appian</strong> , I–II a.d.—List 5</p> <p ><a href=\"#_ftnref23\" name=\"_ftn23\">Jos. </a><strong>Jos.</strong> = Josephus. This abbr. used when follow by title; I a.d.—Lists 5</p> <p ><a href=\"#_ftnref24\" name=\"_ftn24\">ApcSed </a><strong>ApcSed</strong> = Apocalypse of Sedrach—List 2</p> <p ><a href=\"#_ftnref25\" name=\"_ftn25\">GJs </a><strong>GJs</strong> = Gospel of James (Protevangelium Jacobi), II a.d.—List 1</p> <p ><a href=\"#_ftnref26\" name=\"_ftn26\">pers. </a><strong>pers.</strong> = person(s)</p> <p ><a href=\"#_ftnref27\" name=\"_ftn27\">Aristaen </a><strong>Aristaen</strong> , epistologr., V a.d.—List 5</p> <p ><a href=\"#_ftnref28\" name=\"_ftn28\">Ep. </a></p> <p ><strong>Ep.</strong> = Epistola/Epistula, when applied to letters mostly pseudonymous; various dates—List 5</p> <ol> <li>= epistle</li> </ol> <p ><a href=\"#_ftnref29\" name=\"_ftn29\">Sb </a><strong>Sb</strong> = Sammelbuch griechischer Urkunden aus Aegypten—Lists 3, 4</p> <p ><a href=\"#_ftnref30\" name=\"_ftn30\">TestSim </a><strong>TestSim</strong> = Testament of Simeon, s. Test12Patr—List 2</p> <p ><a href=\"#_ftnref31\" name=\"_ftn31\">v.l. </a><strong>v.l.</strong> = varia lectio (variant reading)</p> <p ><a href=\"#_ftnref32\" name=\"_ftn32\">BHHW </a><strong>BHHW</strong> = Biblisch-historisches Handwörterbuch—List 6</p> <p ><a href=\"#_ftnref33\" name=\"_ftn33\">DELG </a><strong>DELG</strong> = PChantraine, Dictionnaire étymologique de la langue grecque—List 6</p> <p ><a href=\"#_ftnref34\" name=\"_ftn34\">M-M </a><strong>M-M</strong> = JMoulton/GMilligan, Vocabulary of Greek Testament—Lists 4, 6</p> <p ><a href=\"#_ftnref35\" name=\"_ftn35\">TW </a><strong>TW</strong> = Theologisches Wörterbuch zum NT; tr. GBromiley, Theological Dictionary of the NT—List 6</p> <p ><a href=\"#_ftnref36\" name=\"_ftn36\">Spicq </a><strong>Spicq</strong> = CS., Lexique théologique du Nouveau Testament—Lists 6</p> <p ><a href=\"#_ftnref37\" name=\"_ftn37\"></a>Arndt, William ; Danker, Frederick W. ; Bauer, Walter: <em>A Greek-English Lexicon of the New Testament and Other Early Christian Literature</em>. 3rd ed. Chicago : University of Chicago Press, 2000, S. 616</p>"}]}