{"word":"μυστήριον","slug":"μυστήριον","sections":[{"paragraph":""},{"paragraph":""},{"paragraph":"<p ><strong><elT>μυστήριον, ου, τό</elT></strong> ‘secret, secret rite, secret teaching, mystery’ a <a href=\"#_ftn1\" name=\"_ftnref1\">relig.</a> <a href=\"#_ftn2\" name=\"_ftnref2\">t.t.</a> (<a href=\"#_ftn3\" name=\"_ftnref3\">predom.</a> <a href=\"#_ftn4\" name=\"_ftnref4\">pl.</a>) applied in the <a href=\"#_ftn5\" name=\"_ftnref5\">Gr-Rom.</a> world mostly to the mysteries w. their secret teachings, relig. and political in nature, concealed within many strange customs and ceremonies. The principal rites remain unknown because of a reluctance in antiquity to divulge them (<a href=\"#_ftn6\" name=\"_ftnref6\">Trag.</a>+; <a href=\"#_ftn7\" name=\"_ftnref7\">Hdt.</a> 2, 51, 2; <a href=\"#_ftn8\" name=\"_ftnref8\">Diod S</a> 1, 29, 3; 3, 63, 2; Socrat., <a href=\"#_ftn9\" name=\"_ftnref9\">Ep.</a> 27, 3; <a href=\"#_ftn10\" name=\"_ftnref10\">Cornutus</a> 28 p. 56, 22; 57, 4; Alciphron 3, 26, 1; <a href=\"#_ftn11\" name=\"_ftnref11\">OGI</a> 331, 54; 528, 13; 721, 2, <a href=\"#_ftn12\" name=\"_ftnref12\">SIG</a> s. index; <a href=\"#_ftn13\" name=\"_ftnref13\">Sb</a> 7567, 9 [III a.d.]; <a href=\"#_ftn14\" name=\"_ftnref14\">PGM</a> 1, 131; 4, 719ff; 2477 <el>τὰ ἱερὰ μ</el>. <el>ἀνθρώποις εἰς γνῶσιν</el>; 5, 110; 12, 331; 13, 128 <el>τὸ μυστήριον τοῦ θεοῦ</el>. Only the perfected gnostic is <el>τῶν μυστηρίων ἀκροατής</el> <a href=\"#_ftn15\" name=\"_ftnref15\">Hippol</a>., Ref. 5, 8, 29.—OKern, D. griech. Mysterien d. klass. Zeit 1927; WOtto, D. Sinn der eleusin. Myst. ’40; MNilsson, The Dionysiac Mysteries of the Hell. and Rom. Age, ’57; <a href=\"#_ftn16\" name=\"_ftnref16\">Kl. Pauly</a> III 1533–42; WBurkert, Antike Mysterien ’90). Also <a href=\"#_ftn17\" name=\"_ftnref17\">LXX</a> and other versions of the <a href=\"#_ftn18\" name=\"_ftnref18\">OT</a> use the word, as well as <a href=\"#_ftn19\" name=\"_ftnref19\">En</a> (of the heavenly secret) and numerous <a href=\"#_ftn20\" name=\"_ftnref20\">pseudepigr.</a>, <a href=\"#_ftn21\" name=\"_ftnref21\">Philo</a>, <a href=\"#_ftn22\" name=\"_ftnref22\">Joseph</a>. (C. Ap. 2, 189, 266), <a href=\"#_ftn23\" name=\"_ftnref23\">apolog.</a> (<a href=\"#_ftn24\" name=\"_ftnref24\">exc.</a> <a href=\"#_ftn25\" name=\"_ftnref25\">Ar.</a>); it is a <a href=\"#_ftn26\" name=\"_ftnref26\">loanw.</a> in <a href=\"#_ftn27\" name=\"_ftnref27\">rabb.</a> Our <a href=\"#_ftn28\" name=\"_ftnref28\">lit.</a> uses <el>μ</el>. in <a href=\"#_ftn29\" name=\"_ftnref29\">ref.</a> to the transcendent activity of God and its impact on God’s people.</p> <p >① <strong>the unmanifested or private counsel of God</strong>, <strong><em>(God’s) secret,</em></strong> the secret thoughts, plans, and dispensations of God (<a href=\"#_ftn30\" name=\"_ftnref30\">SJCh</a> 78, 9; <el>τὸ μ</el>. <el>τῆς μοναρχίας τῆς κατὰ τὸν θεόν</el> <a href=\"#_ftn31\" name=\"_ftnref31\">Theoph. Ant.</a> 2, 28 [p. 166, 17]) which are hidden <a href=\"#_ftn32\" name=\"_ftnref32\">fr.</a> human reason, as well as fr. all other comprehension below the divine level, and await either fulfillment or revelation to those for whom they are intended (the divine Logos as <el>διδάσκαλος θείων μυστηρίων</el> <a href=\"#_ftn33\" name=\"_ftnref33\">Orig</a>., C. Cels. 3, 62, 9: the constellations as <el>δεῖγμα καὶ τύπον … μεγάλου μυστηρίου</el> Hippol. Ant. 2, 15 [p. 138, 7]; Abraham is <el>τῶν θείων … μέτοχος μυστηρίων</el> <a href=\"#_ftn34\" name=\"_ftnref34\">Did.</a>, Gen. 213, 20).</p> <p >ⓐ In the gospels <el>μ</el>. is found only in one context, where Jesus says to the disciples who have asked for an explanation of the parable(s) <el>ὑμῖν τὸ μυστήριον δέδοται τῆς βασιλείας τ</el>. <el>θεοῦ</el> <strong><a class='B' href='B:480 4:11'>Mk 4:11</a></strong>; the synopt. parallels have the pl. <strong><a class='B' href='B:470 13:11'>Mt 13:11</a></strong> (LCerfaux, <a href=\"#_ftn35\" name=\"_ftnref35\">NTS</a> 2, ’55/56, 238–49); <strong><a class='B' href='B:490 8:10'>Lk 8:10</a>.</strong>—WWrede, D. Messiasgeh. in den Evv. 1901; HEbeling, D. Messiasgeh. u. d. Botschaft des Mc-Evangelisten ’39; NJohansson, SvTK 16, ’40, 3–38; OPiper, Interpretation 1, ’47, 183–200; RArida, St Vladimar Theol. Qtly 38, ’94, 211–34 (patristic exegesis <strong><a class='B' href='B:480 4:10-12'>Mk 4:10–12</a></strong> <a href=\"#_ftn36\" name=\"_ftnref36\">par.</a>).</p> <p >ⓑ The Pauline lit. has <el>μ</el>. in 21 places. A <em>secret</em> or <em>mystery,</em> too profound for human ingenuity, is God’s reason for the partial hardening of Israel’s heart <strong><a class='B' href='B:520 11:25'>Ro 11:25</a></strong> or the transformation of the surviving Christians at the Parousia <strong><a class='B' href='B:530 15:51'>1 Cor 15:51</a></strong>. Even Christ, who was understood by so few, is <em>God’s secret</em> or <em>mystery</em> <strong><a class='B' href='B:580 2:2'>Col 2:2</a></strong>, hidden ages ago <strong><a class='B' href='B:580 1:26'>1:26</a></strong> (<a href=\"#_ftn37\" name=\"_ftnref37\">cp.</a> <a href=\"#_ftn38\" name=\"_ftnref38\">Herm. Wr.</a> 1, 16 <el>τοῦτό ἐστι τὸ κεκρυμμένον μυστήριον μέχρι τῆσδε τῆς ἡμέρας</el>), but now gloriously revealed among the gentiles vs. <strong><a class='B' href='B:580 1:27'>27</a></strong>, to whom the <em>secret of Christ,</em> <a href=\"#_ftn39\" name=\"_ftnref39\">i.e.</a> his relevance for them, is proclaimed, <strong><a class='B' href='B:580 4:3'>4:3</a></strong> (CMitton, <a href=\"#_ftn40\" name=\"_ftnref40\">ET</a> 60, ’48/49, 320f). Cp. <strong><a class='B' href='B:520 16:25'>Ro 16:25</a></strong>; <strong><a class='B' href='B:530 2:1'>1 Cor 2:1</a></strong> (cp. <a href=\"#_ftn41\" name=\"_ftnref41\">Just</a>., <a href=\"#_ftn42\" name=\"_ftnref42\">D</a>. 91, 1; 131, 2 <a href=\"#_ftn43\" name=\"_ftnref43\">al.</a> <el>μ</el>. <el>τοῦ σταυροῦ</el>; 74, 3 <el>τὸ σωτήριον τοῦτο μ</el>., <el>τοῦτʼ ἔστι τὸ πάθος τοῦ χριστοῦ</el>). The pl. is used to denote Christian preaching by the apostles and teachers in the <a href=\"#_ftn44\" name=\"_ftnref44\">expr.</a> <el>οἰκονόμοι μυστηρίων θεοῦ</el> <strong><a class='B' href='B:530 4:1'>1 Cor 4:1</a></strong> (<a href=\"#_ftn45\" name=\"_ftnref45\">Iambl</a>., <a href=\"#_ftn46\" name=\"_ftnref46\">Vi.</a> Pyth. 23, 104 calls the teachings of Pyth. <el>θεῖα μυστήρια</el>). Not all Christians are capable of understanding all the mysteries. The one who speaks in tongues <el>πνεύματι λαλεῖ μυστήρια</el> <em>utters secret truths in the Spirit</em> which the person alone shares w. God, and which others, even Christians, do not understand <strong><a class='B' href='B:530 14:2'>1 Cor 14:2</a></strong>. Therefore the possession of <em>all mysteries</em> is a great joy <strong><a class='B' href='B:530 13:2'>13:2</a></strong> (Just., D. 44, 2). And the spirit-filled apostle can say of the highest stage of Christian knowledge, revealed only to the <el>τέλειοι</el>: <el>λαλοῦμεν θεοῦ σοφίαν ἐν μυστηρίῳ</el> <em>we impart the wisdom of God in the form of a mystery</em> (<el>ἐν μυστηρίῳ</el>=in a mysterious manner [Laud. Therap. 11] or =secretly, so that no unauthorized person would learn of it [cp. Cyr. of Scyth. p. 90, 14 <el>ἐν μυστηρίῳ λέγει</el>]) <strong><a class='B' href='B:530 2:7'>2:7</a></strong> (AKlöpper, <a href=\"#_ftn47\" name=\"_ftnref47\">ZWT</a> 47, 1905, 525–45).—Eph, for which (as well as for Col) <el>μ</el>. is a predominant concept, sees the <el>μ</el>. <el>τοῦ θελήματος αὐτοῦ</el> (<a href=\"#_ftn48\" name=\"_ftnref48\">sc.</a> <el>θεοῦ</el>) <strong><a class='B' href='B:530 1:9'>1:9</a></strong> or <el>μ</el>. <el>τ</el>. <el>Χριστοῦ</el> <strong><a class='B' href='B:530 3:4'>3:4</a></strong> or <el>μ</el>. <el>τ</el>. <el>εὐαγγελίου</el> <strong><a class='B' href='B:530 6:19'>6:19</a></strong> in acceptance of the gentiles as Christians <strong><a class='B' href='B:530 3:3'>3:3ff</a></strong>, <strong><a class='B' href='B:530 3:9'>9ff.</a></strong> A unique <em>great mystery</em> is revealed <strong><a class='B' href='B:530 5:32'>5:32</a></strong>, where the relation <a href=\"#_ftn49\" name=\"_ftnref49\">betw.</a> Christ and the Christian community or church is spoken of on the basis of <a class='B' href='B:10 2:24'>Gen 2:24</a> (cp. the interpretation of the sun as symbol of God, Theoph. Ant. 2, 15 [p. 138, 8], and s. WKnox, St. Paul and the Church of the Gentiles, ’39, 183f; 227f; WBieder, <a href=\"#_ftn50\" name=\"_ftnref50\">TZ</a> 11, ’55, 329–43).</p> <p >ⓒ In Rv <el>μ</el>. is used in ref. to the mysterious things portrayed there. The whole content of the book appears as <el>τὸ μ</el>. <el>τοῦ θεοῦ</el> <strong><a class='B' href='B:530 10:7'>10:7.</a></strong> Also <el>τὸ μ</el>. <el>τῶν ἑπτὰ ἀστέρων</el> <strong><a class='B' href='B:530 1:20'>1:20</a></strong>; <el>τὸ μ</el>. <el>τῆς γυναικός</el> <strong><a class='B' href='B:530 17:7'>17:7</a></strong>, cp. vs. <strong><a class='B' href='B:530 17:5'>5</a></strong>, where in each case <el>μ</el>. may mean <em>allegorical significance</em> (so BEaston, Pastoral Epistles ’47, 215).</p> <p >② <strong>that which transcends normal understanding</strong>, <strong><em>transcendent/ultimate reality, secret,</em></strong> with focus on <a href=\"#_ftn51\" name=\"_ftnref51\">Israelite/Christian</a> experience.</p> <p >ⓐ 1 Ti uses <el>μ</el>. as a formula: <el>τὸ μ</el>. <el>τῆς πίστεως</el> is simply <em>faith</em> <strong><a class='B' href='B:530 3:9'>3:9.</a></strong> <el>τὸ τ</el>. <el>εὐσεβείας μ</el>. <em>the secret of (our) piety</em> vs. <strong><a class='B' href='B:530 3:16'>16.</a></strong>—<el>τὸ μ</el>. <el>τῆς ἀνομίας</el> <strong><a class='B' href='B:600 2:7'>2 Th 2:7</a></strong> s. <elT><a class='T' href='S:ἀνομία'>ἀνομία</a></elT> 1 (<a href=\"#_ftn52\" name=\"_ftnref52\">Jos.</a>, Bell. 1, 470 calls the life of Antipater <el>κακίας μυστήριον</el> because of his baseness practiced in secret. Cp. also <a href=\"#_ftn53\" name=\"_ftnref53\">SibOr</a> 8, 58 <el>τὰ πλάνης μυστήρια</el>; 56).—PFurfey, <a href=\"#_ftn54\" name=\"_ftnref54\">CBQ</a> 8, ’46, 179–91.</p> <p >ⓑ in <a href=\"#_ftn55\" name=\"_ftnref55\">Ign.</a>: the death and resurrection of Jesus as <el>μ</el>. <a href=\"#_ftn56\" name=\"_ftnref56\">IMg</a> 9:1 (<el>τὸ περὶ τῆς ἀναστάσεως μ</el>. Orig., C. Cels. 1, 7, 9). The virginity of Mary, her childbearing, and the Lord’s death are called <el>τρία μ</el>. <el>κραυγῆς</el> <em>three mysteries (to be) loudly proclaimed</em> <a href=\"#_ftn57\" name=\"_ftnref57\">IEph</a> 19:1 (they are mysteries because they go so contrary to human expectation). So also of the annunciation to Mary and her conception <a href=\"#_ftn58\" name=\"_ftnref58\">GJs</a> 12:2f. The deacons are <el>οἱ διάκονοι μυστηρίων Ἰ</el>. <el>Χρ</el>. <a href=\"#_ftn59\" name=\"_ftnref59\">ITr</a> 2:3.</p> <p >ⓒ Quite difficult is the saying about the tried and true prophet <el>ποιῶν εἰς μυστήριον κοσμικὸν ἐκκλησίας</el> <em>who acts in accord with the earthly mystery of (God’s) assembly</em> D 11:11. This may refer to celibacy; the prophet lives in such a way as to correspond to the relation betw. Christ and the people of God; cp. <strong><a class='B' href='B:560 5:32'>Eph 5:32</a></strong> (so Harnack, <a href=\"#_ftn60\" name=\"_ftnref60\">TU</a> II 1; 2, 1884, 44ff; HWeinel, Die Wirkungen d. Geistes u. der Geister 1899, 131–38; PDrews, <a href=\"#_ftn61\" name=\"_ftnref61\">Hdb.</a> z. d. ntl. Apokryphen 1904, 274ff; RKnopf, Hdb. <a href=\"#_ftn62\" name=\"_ftnref62\">ad loc.</a>—Differently CTaylor, The Teaching of the Twelve Apost. 1886, 82–92; RHarris, The Teaching of the Ap. 1887; FFunk, Patr. Apostol.<sup>2</sup> 1901 ad loc.; <a href=\"#_ftn63\" name=\"_ftnref63\">Zahn</a>, Forschungen III 1884, 301).</p> <p >ⓓ <el>μ</el>. occurs <a href=\"#_ftn64\" name=\"_ftnref64\">oft.</a> in <a href=\"#_ftn65\" name=\"_ftnref65\">Dg</a>: <el>τὸ τῆς θεοσεβείας μ</el>. <em>the secret of (our) piety</em> 4:6 (what Dg means by <el>μ</el>. is detailed in <a href=\"#_ftn66\" name=\"_ftnref66\">ch.</a> 5). Likew. of Christian teaching (cp. <a href=\"#_ftn67\" name=\"_ftnref67\">Ps.</a>-Phocyl. 229 and comments by <a href=\"#_ftn68\" name=\"_ftnref68\">Horst</a> 260–61) <el>πατρὸς μυστήρια</el> 11:2; cp. vs. 5. Hence the Christian can <el>μυστήρια θεοῦ λαλεῖν</el> 10:7. In contrast to <el>ἀνθρώπινα μ</el>. 7:1. <el>οὗ</el> (sc. <el>τ</el>. <el>θεοῦ</el>) <el>τὰ μυστήρια</el> <em>whose secret counsels</em> 7:2 (the divine will for orderly management of the universe). Of God keeping personal counsel <el>κατεῖχεν ἐν μυστηρίῳ … τὴν σοφὴν αὐτοῦ βουλήν</el> 8:10.—<a href=\"#_ftn69\" name=\"_ftnref69\">Lghtf.</a>, St. Paul’s Ep. to the Col. and Phlm. p. 167ff; JRobinson, St. Paul’s Ep. to the Eph. 1904, 234ff; GWobbermin, Religionsgesch. Studien 1896, 144ff; EHatch, Essays on Bibl. <a href=\"#_ftn70\" name=\"_ftnref70\">Gk.</a> 1889, 57ff; HvSoden, <a href=\"#_ftn71\" name=\"_ftnref71\">ZNW</a> 12, 1911, 188ff; TFoster, <a href=\"#_ftn72\" name=\"_ftnref72\">AJT</a> 19, 1915, 402–15; OCasel, D. Liturgie als Mysterienfeier<sup>5</sup> 1923; JSchneider, ‘Mysterion’ im <a href=\"#_ftn73\" name=\"_ftnref73\">NT</a>: <a href=\"#_ftn74\" name=\"_ftnref74\">StKr</a> 104, ’32, 255–78; TArvedson, D. Mysterium Christi ’37; KPrümm, ‘Mysterion’ v. Pls bis Orig.: <a href=\"#_ftn75\" name=\"_ftnref75\">ZKT</a> 61, ’37, 391–425, <a href=\"#_ftn76\" name=\"_ftnref76\">Biblica</a> 37, ’56, 135–61; RBrown, The Semitic Background of ‘Mystery’ in the NT, ’68; cp. KKuhn, NTS 7, 61, 366 for Qumran parallels to various passages in Eph and Ro; ABöhlig, Mysterion u. Wahrheit, ’68, 3–40; JFruytier, Het woord M. in de catechesen van Cyrillus van Jerusalem, ’50; ANock, Hellenistic Mysteries and Christian Sacraments, Essays on Religion and the Ancient World II, ’72, 790–820; AHarvey, The Use of Mystery Language in the Bible: <a href=\"#_ftn77\" name=\"_ftnref77\">JTS</a> 31, ’80, 320–36.—<a href=\"#_ftn78\" name=\"_ftnref78\">DELG</a> <a href=\"#_ftn79\" name=\"_ftnref79\">s.v.</a> <elT><a class='T' href='S:καμμύω'>μύω</a></elT>. <a href=\"#_ftn80\" name=\"_ftnref80\">M-M</a>. <a href=\"#_ftn81\" name=\"_ftnref81\">EDNT</a>. <a href=\"#_ftn82\" name=\"_ftnref82\">TW</a>. <a href=\"#_ftn83\" name=\"_ftnref83\">Sv</a>.</p> <p ><a href=\"#_ftn84\" name=\"_ftnref84\"></a></p> <p ><a href=\"#_ftnref1\" name=\"_ftn1\">relig. </a><strong>relig.</strong> = religious</p> <p ><a href=\"#_ftnref2\" name=\"_ftn2\">t.t. </a><strong>t.t.</strong> = terminus technicus (termini technici), technical term(s)</p> <p ><a href=\"#_ftnref3\" name=\"_ftn3\">predom. </a><strong>predom.</strong> = predominant(ly)</p> <ol> <li><a href=\"#_ftnref4\" name=\"_ftn4\"> </a><strong>pl.</strong> = plural</li> </ol> <p ><a href=\"#_ftnref5\" name=\"_ftn5\">Gr-Rom. </a><strong>Gr-Rom.</strong> = Greco-Roman (gener. in contrast to Israelite/Christian tradition)</p> <p ><a href=\"#_ftnref6\" name=\"_ftn6\">Trag. </a></p> <p ><strong>Trag.</strong> = writer (s) of tragedy</p> <p ><strong>trag.</strong> = tragedy, writer (s) of tragedy</p> <p ><a href=\"#_ftnref7\" name=\"_ftn7\">Hdt. </a><strong>Hdt.</strong> = Herodotus, V b.c.—List 5</p> <p ><a href=\"#_ftnref8\" name=\"_ftn8\">Diod S </a><strong>Diod S</strong> , I b.c.—List 5</p> <p ><a href=\"#_ftnref9\" name=\"_ftn9\">Ep. </a></p> <p ><strong>Ep.</strong> = Epistola/Epistula, when applied to letters mostly pseudonymous; various dates—List 5</p> <ol> <li>= epistle</li> </ol> <p ><a href=\"#_ftnref10\" name=\"_ftn10\">Cornutus </a><strong>Cornutus</strong> , I a.d.—List 5</p> <p ><a href=\"#_ftnref11\" name=\"_ftn11\">OGI </a><strong>OGI</strong> = Orientis Graeci Inscriptiones Selectae—List 3</p> <p ><a href=\"#_ftnref12\" name=\"_ftn12\">SIG </a><strong>SIG</strong> = Sylloge Inscriptionum Graecarum<sup>3</sup>; superscript omitted in text—List 3</p> <p ><a href=\"#_ftnref13\" name=\"_ftn13\">Sb </a><strong>Sb</strong> = Sammelbuch griechischer Urkunden aus Aegypten—Lists 3, 4</p> <p ><a href=\"#_ftnref14\" name=\"_ftn14\">PGM </a><strong>PGM</strong> = Papyri Graecae Magicae—List 4</p> <p ><a href=\"#_ftnref15\" name=\"_ftn15\">Hippol </a><strong>Hippol</strong> , II–III a.d.—List 5</p> <p ><a href=\"#_ftnref16\" name=\"_ftn16\">Kl. Pauly </a><strong>Kl. Pauly</strong> = Der Kleine Pauly: Lexikon der Antike—List 6</p> <p ><a href=\"#_ftnref17\" name=\"_ftn17\">LXX </a><strong>LXX</strong> = Septuaginta, ed. ARahlfs, unless otherwise specified—Lists 2, beg.</p> <p ><a href=\"#_ftnref18\" name=\"_ftn18\">OT </a><strong>OT</strong> = Old Testament</p> <p ><a href=\"#_ftnref19\" name=\"_ftn19\">En </a><strong>En</strong> = I Enoch—List 2</p> <p ><a href=\"#_ftnref20\" name=\"_ftn20\">pseudepigr. </a><strong>pseudepigr.</strong> = pseudepigraphon, pseudepigrapha</p> <p ><a href=\"#_ftnref21\" name=\"_ftn21\">Philo </a><strong>Philo</strong> = P. of Alexandria, I b.c.–I a.d.—List 5</p> <p ><a href=\"#_ftnref22\" name=\"_ftn22\">Joseph </a><strong>Joseph</strong> This abbr. used when no specific texts are cited (s. Jos.); I a.d.—List 5</p> <p ><a href=\"#_ftnref23\" name=\"_ftn23\">apolog. </a><strong>apolog.</strong> = apologist(s)</p> <p ><a href=\"#_ftnref24\" name=\"_ftn24\">exc. </a><strong>exc.</strong> = except</p> <p ><a href=\"#_ftnref25\" name=\"_ftn25\">Ar. </a><strong>Ar.</strong> = Aristides, apologist, II a.d.—List 5</p> <p ><a href=\"#_ftnref26\" name=\"_ftn26\">loanw. </a><strong>loanw.</strong> = loanword</p> <p ><a href=\"#_ftnref27\" name=\"_ftn27\">rabb. </a><strong>rabb.</strong> = rabbinical (literature etc.)</p> <p ><a href=\"#_ftnref28\" name=\"_ftn28\">lit. </a><strong>lit.</strong> = literal(ly); literature (refererences to [scholarly] literature)</p> <p ><a href=\"#_ftnref29\" name=\"_ftn29\">ref. </a><strong>ref.</strong> = reference(s)</p> <p ><a href=\"#_ftnref30\" name=\"_ftn30\">SJCh </a><strong>SJCh</strong> = Sophia Jesu Christi—List 1</p> <p ><a href=\"#_ftnref31\" name=\"_ftn31\">Theoph. Ant. </a><strong>Theoph. Ant.</strong> = Theophilus Antiochenus, II a.d.—List 5</p> <ol> <li><a href=\"#_ftnref32\" name=\"_ftn32\"> </a><strong>fr.</strong> = from</li> </ol> <p ><a href=\"#_ftnref33\" name=\"_ftn33\">Orig </a><strong>Orig</strong> , var. works, II–III a.d.—List 5</p> <p ><a href=\"#_ftnref34\" name=\"_ftn34\">Did. </a><strong>Did.</strong> = Didymus Caecus (the Blind), commentator on OT books, IV a.d.—List 5</p> <p ><a href=\"#_ftnref35\" name=\"_ftn35\">NTS </a><strong>NTS</strong> = New Testament Studies—List 6</p> <p ><a href=\"#_ftnref36\" name=\"_ftn36\">par. </a><strong>par.</strong> = parallel</p> <ol> <li><a href=\"#_ftnref37\" name=\"_ftn37\"> </a><strong>cp.</strong> = compare, freq. in ref. to citation fr. ancient texts</li> </ol> <p ><a href=\"#_ftnref38\" name=\"_ftn38\">Herm. Wr. </a><strong>Herm. Wr.</strong> = Hermetic Writings—List 5</p> <p ><a href=\"#_ftnref39\" name=\"_ftn39\">i.e. </a></p> <p ><strong>i.e.</strong> = id est (that is)</p> <p ><strong>I.-E.</strong> Indo-European</p> <p ><a href=\"#_ftnref40\" name=\"_ftn40\">ET </a><strong>ET</strong> = Expository Times—List 6</p> <p ><a href=\"#_ftnref41\" name=\"_ftn41\">Just </a><strong>Just</strong> , II a.d.—List 5</p> <p ><a href=\"#_ftnref42\" name=\"_ftn42\">D </a><strong>D</strong> = Didache, except that in a list of manuscripts or as textual variant D refers to Codex Bezae—List 1</p> <ol> <li><a href=\"#_ftnref43\" name=\"_ftn43\"> </a><strong>al.</strong> =alibi (elsewhere), aliter (otherwise), alii (others)</li> </ol> <p ><a href=\"#_ftnref44\" name=\"_ftn44\">expr. </a><strong>expr.</strong> = expression</p> <p ><a href=\"#_ftnref45\" name=\"_ftn45\">Iambl </a><strong>Iambl</strong> , phil., III–IV a.d.—List 5</p> <p ><a href=\"#_ftnref46\" name=\"_ftn46\">Vi. </a><strong>Vi.</strong> = Vita, Vitae</p> <p ><a href=\"#_ftnref47\" name=\"_ftn47\">ZWT </a><strong>ZWT</strong> = Zeitschrift für Wissenschaftliche Theologie—List 6</p> <ol> <li><a href=\"#_ftnref48\" name=\"_ftn48\"> </a><strong>sc.</strong> = scilicet (one may understand, supply)</li> </ol> <p ><a href=\"#_ftnref49\" name=\"_ftn49\">betw. </a><strong>betw.</strong> = between</p> <p ><a href=\"#_ftnref50\" name=\"_ftn50\">TZ </a><strong>TZ</strong> = Theologische Zeitschrift—List 6</p> <p ><a href=\"#_ftnref51\" name=\"_ftn51\">Israelite/Christian </a><strong>Israelite/Christian</strong> = Israelite or Christian or both in contrast to Gr-Rom</p> <p ><a href=\"#_ftnref52\" name=\"_ftn52\">Jos. </a><strong>Jos.</strong> = Josephus. This abbr. used when follow by title; I a.d.—Lists 5</p> <p ><a href=\"#_ftnref53\" name=\"_ftn53\">SibOr </a><strong>SibOr</strong> = Oracula Sibyllina, II–III a.d.—List 5</p> <p ><a href=\"#_ftnref54\" name=\"_ftn54\">CBQ </a><strong>CBQ</strong> = Catholic Biblical Quarterly—List 6</p> <p ><a href=\"#_ftnref55\" name=\"_ftn55\">Ign. </a><strong>Ign.</strong> = Ignatius; always simply I. when cited with one of his epistles</p> <p ><a href=\"#_ftnref56\" name=\"_ftn56\">IMg </a><strong>IMg</strong> = Ignatius to the Magnesians—List 1</p> <p ><a href=\"#_ftnref57\" name=\"_ftn57\">IEph </a><strong>IEph</strong> = Ignatius to the Ephesians—List 1</p> <p ><a href=\"#_ftnref58\" name=\"_ftn58\">GJs </a><strong>GJs</strong> = Gospel of James (Protevangelium Jacobi), II a.d.—List 1</p> <p ><a href=\"#_ftnref59\" name=\"_ftn59\">ITr </a><strong>ITr</strong> = Ignatius to the Trallians—List 1</p> <p ><a href=\"#_ftnref60\" name=\"_ftn60\">TU </a><strong>TU</strong> = Texte und Untersuchungen—List 6</p> <p ><a href=\"#_ftnref61\" name=\"_ftn61\">Hdb. </a><strong>Hdb.</strong> = Handbuch (in connection with a specific NT book, the ref. is to a commentary in the series Handbuch zum Neuen Testament, founded by HLietzmann)—List 6</p> <p ><a href=\"#_ftnref62\" name=\"_ftn62\">ad loc. </a><strong>ad loc.</strong> = ad locum (to or at the place under consideration)</p> <p ><a href=\"#_ftnref63\" name=\"_ftn63\">Zahn </a><strong>Zahn</strong> = TZ., various works—List 6</p> <p ><a href=\"#_ftnref64\" name=\"_ftn64\">oft. </a><strong>oft.</strong> = often</p> <p ><a href=\"#_ftnref65\" name=\"_ftn65\">Dg </a><strong>Dg</strong> = Letter of Diognetus, attributed to an unidentifiable apologist; II a.d.—List 1</p> <ol> <li><a href=\"#_ftnref66\" name=\"_ftn66\"> </a><strong>ch.</strong> = chapter(s)</li> </ol> <p ><a href=\"#_ftnref67\" name=\"_ftn67\">Ps. </a><strong>Ps.</strong> = pseudo, pseudonymous</p> <p ><a href=\"#_ftnref68\" name=\"_ftn68\">Horst </a><strong>Horst</strong> = PvanderHorst, s. Ps.-Phocyl(ides)—List 5</p> <p ><a href=\"#_ftnref69\" name=\"_ftn69\">Lghtf. </a><strong>Lghtf.</strong> = JBLightfoot</p> <p ><a href=\"#_ftnref70\" name=\"_ftn70\">Gk. </a><strong>Gk.</strong> = Greek</p> <p ><a href=\"#_ftnref71\" name=\"_ftn71\">ZNW </a><strong>ZNW</strong> = Zeitschrift für die ntl. Wissenschaft—List 6</p> <p ><a href=\"#_ftnref72\" name=\"_ftn72\">AJT </a><strong>AJT</strong> = American Journal of Theology—List 6</p> <p ><a href=\"#_ftnref73\" name=\"_ftn73\">NT </a><strong>NT</strong> = New Testament</p> <p ><a href=\"#_ftnref74\" name=\"_ftn74\">StKr </a><strong>StKr</strong> = Theologische Studien und Kritiken—List 6</p> <p ><a href=\"#_ftnref75\" name=\"_ftn75\">ZKT </a><strong>ZKT</strong> = Zeitschrift für katholische Theologie—List 6</p> <p ><a href=\"#_ftnref76\" name=\"_ftn76\">Biblica </a><strong>Biblica</strong> (unabbr.)—List 6</p> <p ><a href=\"#_ftnref77\" name=\"_ftn77\">JTS </a><strong>JTS</strong> = Journal of Theological Studies—List 6</p> <p ><a href=\"#_ftnref78\" name=\"_ftn78\">DELG </a><strong>DELG</strong> = PChantraine, Dictionnaire étymologique de la langue grecque—List 6</p> <p ><a href=\"#_ftnref79\" name=\"_ftn79\">s.v. </a><strong>s.v.</strong> = sub voce (under the word, look up the word)</p> <p ><a href=\"#_ftnref80\" name=\"_ftn80\">M-M </a><strong>M-M</strong> = JMoulton/GMilligan, Vocabulary of Greek Testament—Lists 4, 6</p> <p ><a href=\"#_ftnref81\" name=\"_ftn81\">EDNT </a><strong>EDNT</strong> = Exegetical Dictionary of the NT—List 6</p> <p ><a href=\"#_ftnref82\" name=\"_ftn82\">TW </a><strong>TW</strong> = Theologisches Wörterbuch zum NT; tr. GBromiley, Theological Dictionary of the NT—List 6</p> <p ><a href=\"#_ftnref83\" name=\"_ftn83\">Sv </a><strong>Sv</strong> (at the end of entries)=HSieben, Voces—List 6</p> <p ><a href=\"#_ftnref84\" name=\"_ftn84\"></a>Arndt, William ; Danker, Frederick W. ; Bauer, Walter: <em>A Greek-English Lexicon of the New Testament and Other Early Christian Literature</em>. 3rd ed. Chicago : University of Chicago Press, 2000, S. 661</p>"}]}