{"word":"G4863 - συνάγω - synágō - soon-ag'-o - + accompany","slug":"G4863","sections":[{"paragraph":""},{"paragraph":"<strong>Original: </strong><span class=\"hebrewOrGreek\">συνάγω</span>"},{"paragraph":"<strong>Transliteration: </strong>synágō"},{"paragraph":"<strong>Phonetic: </strong>soon-ag'-o"},{"paragraph":"<strong>Short Definition: </strong>+ accompany"},{"paragraph":""},{"paragraph":"<b>&#x03C3;&#x03C5;&#x03BD;&#x03B1;&#x0301;&#x03B3;&#x03C9; - sunago&#x0304;</b> - <i>soon-ag'-o</i><p/>From <a href=\"#/G4862\">G4862</a> and <a href=\"#/G71\">G71</a>; to <i>lead together</i>, that is, <i>collect</i> or <i>convene</i>; specifically to <i>entertain</i> (hospitably): - + accompany, assemble (selves, together), bestow, come together, gather (selves together, up, together), lead into, resort, take in."}]}