{"word":"G5516 - χξϛ - chx stigma - khee xee stig'-ma - Six hundred threescore and six","slug":"G5516","sections":[{"paragraph":""},{"paragraph":"<strong>Original: </strong><span class=\"hebrewOrGreek\">χξϛ</span>"},{"paragraph":"<strong>Transliteration: </strong>chx stigma"},{"paragraph":"<strong>Phonetic: </strong>khee xee stig'-ma"},{"paragraph":"<strong>Short Definition: </strong>Six hundred threescore and six"},{"paragraph":""},{"paragraph":"<b>&#x03C7;&#x03BE;&#x03C2; - chi xi stigma</b> - <i>khee xee stig'-ma</i><p/>The 22nd, 14th and an obsolete letter (<a href=\"#/G4742\">G4742</a> as a <i>cross</i>) of the Greek alphabet (intermediate between the 5th and 6th), used as numbers; denoting respectively 600, 60 and 6; 666 as a numeral: - six hundred threescore and six."}]}