{"word":"H7929 - שִׁכְמָה - shikmâh - shik-maw' - Shoulder blade","slug":"H7929","sections":[{"paragraph":""},{"paragraph":"<strong>Original: </strong><span class=\"hebrewOrGreek\">שִׁכְמָה</span>"},{"paragraph":"<strong>Transliteration: </strong>shikmâh"},{"paragraph":"<strong>Phonetic: </strong>shik-maw'"},{"paragraph":"<strong>Short Definition: </strong>Shoulder blade"},{"paragraph":""},{"paragraph":"<b>&#x05E9;&#x05C1;&#x05DB;&#x05DE;&#x05D4; - shikma&#x0302;h</b> - <i>shik-maw'</i><p/>Feminine of <a href=\"#/H7926\">H7926</a>; the <i>shoulder</i> bone: - shoulder blade."},{"paragraph":""},{"paragraph":"<strong>Cognate:</strong> <a href=\"#/H7925\">H7925</a>, <a href=\"#/H7926\">H7926</a>, <a href=\"#/H7927\">H7927</a>, <a href=\"#/H7928\">H7928</a>, <a href=\"#/H7930\">H7930</a>"}]}