{"word":"G305 - ἀναβαίνω - anabaínō - an-ab-ah'-ee-no - Arise","sections":[{"paragraph":""},{"paragraph":"<strong>மூல வார்த்தை / Original: </strong><span class=\"hebrewOrGreek\">ἀναβαίνω</span>"},{"paragraph":"<strong>எழுத்துமாற்றம் / Transliteration: </strong>anabaínō"},{"paragraph":"<strong>ஒலிபெயர்ப்பு / Phonetic: </strong>an-ab-ah'-ee-no"},{"paragraph":"<strong>சுருக்க விளக்கம் / Short Definition: </strong>Arise"},{"paragraph":""},{"paragraph":"வினைச்சொல் - ஏறு, முன்னேறு, கரையேறு, வளர், அகப்படு, போ, ஏறிப்போ, எழும்பு, வந்தெட்டியிரு, பரம்பு"},{"paragraph":""},{"paragraph":"to go up, move to a higher place, ascend, in a wider sense of things rising up, to rise, mount, be borne up, spring up"},{"paragraph":""},{"paragraph":"<span class=\"spacer\"></span>"},{"paragraph":"<span class=\"parts-of-speech\"><strong>Part(s) of speech:</strong> Verb / வினைச்சொல்</span>"},{"paragraph":"<span class=\"spacer\"></span>"},{"paragraph":"<span class=\"original-in-english\"><strong>ஆங்கில மூலம் / Original in English:</strong> From <a href=\"#/G303 - ἀνά - aná - an-ah'/303\">G303</a> and the base of <a href=\"#/G939 - βάσις - básis - bas'-ece/939\">G939</a>; to <i>go up</i> (literally or figuratively): - arise, ascend (up), climb (go, grow, rise, spring) up, come (up)."},{"paragraph":"<span class=\"spacer\"></span>"},{"paragraph":"<strong>Cognate:</strong> <a href=\"#/G2597 - καταβαίνω - katabaínō - kat-ab-ah'-ee-no/2597\">G2597</a>, <a href=\"#/G305 - ἀναβαίνω - anabaínō - an-ab-ah'-ee-no/305\">G305</a>, <a href=\"#/G3397 - μικρόν - mikrón - mik-ron'/3397\">G3397</a>"}]}