{"word":"ρήγνυμι","slug":"ρήγνυμι","sections":[{"paragraph":""},{"paragraph":""},{"paragraph":"<el><b>ρήγνυμι</b></el> <p/><div class='li500'><b>I. </b><i>to break, break asunder</i> or <i>in pieces, rend, shiver, shatter</i>, <b><a href='S:Homer'>Hom.</a></b>, <a href='S:et cetera'>etc.</a>:—<i>to rend</i> garments, in sign of grief, <b><a href='S:Aeschylus'>Aesch.</a></b>:—<a href='S:Medium, Middle'>Mid.</a> <i>to break for oneself, get broken</i>, <b><a href='S:Iliad'>Il.</a></b><p/></div><div class='li750'><b>2. </b><i>to break</i> a line of battle or body of men, <b><a href='S:Iliad'>Il.</a></b>, <b><a href='S:Herodotus'>Hdt.</a></b>; in <a href='S:Medium, Middle'>Mid.</a>, <el>ρήξασθαι φάλαγγας, στίχας</el> <i>to break oneself a way through</i> the lines, <b><a href='S:Iliad'>Il.</a></b>; <a href='S:absolute, absolutely'>absol.</a>, <el>ρήξασθαι</el> <i>to break</i> or <i>force one's</i> way, <b><a href='S:Iliad'>Il.</a></b><p/></div><div class='li750'><b>3. </b><i>to let break loose, let loose</i>, <b><a href='S:Iliad'>Il.</a></b><p/></div><div class='li750'><b>4. </b><el>ρῆξαι φωνήν</el> <i>to let loose</i> the voice, of children and persons who have been dumb <i>breaking into speech</i>, <b><a href='S:Herodotus'>Hdt.</a></b>: then <i>to speak freely, speak out</i> (like <i>rumpere vocem</i>, <b>Virgil</b>), <b><a href='S:Herodotus'>Hdt.</a></b>, <b><a href='S:Aristophanes'>Ar.</a></b>, <a href='S:et cetera'>etc.</a><p/></div><div class='li750'><b>5. </b><el>δακρύων ρήξασα νάματα</el> <i>having let loose</i> floods of tears, <b><a href='S:Sophocles'>Soph.</a></b>; so, <el>ρ. κλαυθμόν</el> <b><a href='S:Plutarch'>Plut.</a></b><p/></div><div class='li500'><b>II. </b><a href='S:absolute, absolutely'>absol.</a> in the form <el>ρήσσω</el>, <i>to beat the ground, dance</i>, <b><a href='S:Iliad'>Il.</a></b><p/></div><div class='li500'><b>III. </b>later, as a term of fighters, <i>to fell, knock down</i>, <b><a href='S:Demosthenes'>Dem.</a></b><p/></div><div class='li250'><b>B. </b><a href='S:passive signification'><a href='S:Passive Voice'>Pass.</a></a>, mostly used in aor2 <el>ἐρράγην [α]</el>, <i>to break, burst</i>, of waves, <b><a href='S:Iliad'>Il.</a></b>; of clouds, <b><a href='S:Aristophanes'>Ar.</a></b><p/></div><div class='li750'><b>2. </b><i>to break asunder, be rent</i>, of the earth in an earthquake, <b><a href='S:Plato'>Plat.</a></b>; of garments, <b><a href='S:Xenophon'>Xen.</a></b><p/></div><div class='li750'><b>3. </b><i>to burst forth</i>, like lightning, <b><a href='S:Aristophanes'>Ar.</a></b><p/></div><div class='li750'><b>4. </b>of ships, <i>to be wrecked</i>, <b><a href='S:Demosthenes'>Dem.</a></b>: <a href='S:metaphorically'>metaph.</a> of hopes, <b><a href='S:Aeschylus'>Aesch.</a></b><p/></div><div class='li250'><b>C. </b><a href='S:intransitive'>intr.</a>, like <a href='S:passive signification'><a href='S:Passive Voice'>Pass.</a></a>, <i>to break forth</i>, of a river, <i>to break its bounds</i>, <b><a href='S:Herodotus'>Hdt.</a></b>:—<a href='S:metaphorically'>metaph.</a> of sudden misfortunes, bursts of passion, <b><a href='S:Sophocles'>Soph.</a></b><p/></div><div class='li500'><b>II. </b>in this <a href='S:intransitive'>intr.</a> sense the <a href='S:perfect tense'>perf.</a> <el>ἔρρωγα</el> is commonly used of tears, <b><a href='S:Sophocles'>Soph.</a></b>; <a href='S:metaphorically'>metaph.</a>, <el>κακῶν πέλαγος ἔρρωγεν</el> <b><a href='S:Aeschylus'>Aesch.</a></b>, <a href='S:et cetera'>etc.</a><p/></div>"}]}