{"word":"ρᾳδιουργός","slug":"ρᾳδιουργός","sections":[{"paragraph":""},{"paragraph":""},{"paragraph":"<el><b>ρᾳδιουργός</b></el> <el>(ρᾳδι-ουργός, όν) </el><br/><b><a href='S:Etymology'>Etym.</a> </b>*<a href='S:ἔργω'><el>ἔργω</el></a>\n<p/><div class='li750'><b>1. </b>properly, <i>doing things easily;</i> in bad sense, <i>unscrupulous, reckless</i>, <b><a href='S:Aristotle'>Arist.</a></b><p/></div><div class='li750'><b>2. </b>of things, <i>impure</i>, <b><a href='S:Xenophon'>Xen.</a></b><p/></div>"}]}