{"word":"ἀναγωγή","slug":"ἀναγωγή","sections":[{"paragraph":""},{"paragraph":""},{"paragraph":"<el><b>ἀναγωγή</b></el> <br/><b><a href='S:Etymology'>Etym.</a> </b><a href='S:ἀνάγω'><el>ἀνάγω</el></a>\n<p/><div class='li500'><b>I. </b><i>a leading up</i>, <a href='S:especially'>esp.</a> <i>taking a ship into the high sea, a putting to sea</i>, <b><a href='S:Thucydides'>Thuc.</a></b>, <a href='S:et cetera'>etc.</a><p/></div><div class='li500'><b>II. </b><i>a bringing back: restitution</i> by law, <b><a href='S:Plato'>Plat.</a></b><p/></div>"}]}