{"word":"ἑξαετής","slug":"ἑξαετής","sections":[{"paragraph":""},{"paragraph":""},{"paragraph":"<el><b>ἑξαετής</b></el> <el>(ἑξα-ετής, ές) </el>adj (e(ca-et hs_es suff_acc) <p/>adj (e(ca-et hs_es stem_acc) <p/>n (e(caet is_idos stem_acc) <p/><br/><b><a href='S:Etymology'>Etym.</a> </b><a href='S:ἔτος'><el>ἔτος</el></a>\n<p/><div class='li500'><b>I. </b><i>six years old</i>: <a href='S:feminine'>fem.</a> <el>ἑξαέτις</el>, <b><a href='S:Theocritus'>Theocr.</a></b><p/></div><div class='li500'><b>II. </b><i>of six years</i>, <el>χρόνος</el> <b><a href='S:Plutarch'>Plut.</a></b>:—<a href='S:Adverb'>adv.</a>, <el>ἑξάετες</el>, <i>for six years</i>, <b><a href='S:Odyssey'>Od.</a></b><p/></div>"}]}