{"word":"ἐλευθερία","slug":"ἐλευθερία","sections":[{"paragraph":""},{"paragraph":""},{"paragraph":"<b><el>ἐλευϑερία, ας, ἡ</el></b> [<a class=\"G\" href=\"S:✎ s.\">s.</a> next entry] ‘absence of constraint relating to personal choice or action’, <b>freedom, liberty<p class=\"pp3\"/>—<pp>a.</pp></b> liberation from Mosaic legal constraint <b><a href='B:550 2:4'>Gal 2:4</a>; <a href='B:550 5:1'>5:1</a>, <a href='B:550 5:13'>13</a>;</b> in related vein <b><a href='B:530 10:29'>1 Cor 10:29</a>; <a href='B:540 3:17'>2 Cor 3:17</a>; <a href='B:660 1:25'>Js 1:25</a>; <a href='B:660 2:12'>2:12</a>.<p class=\"pp3\"/>—<pp>b.</pp></b> freedom of God’s people in general<b> <a href='B:670 2:16'>1 Pt 2:16</a>.<p class=\"pp3\"/>—<pp>c.</pp></b> illegitimate understanding of freedom as license <b><a href='B:680 2:19'>2 Pt 2:19</a>.</b> <center id=\"nav_bottom\"> <a id=\"left_arrow\" href=\"S:ἔλεος\">&ensp;&ensp;&ensp;&ensp;</a> <a id=\"bottom_home\" href=\"S:#1.Table of Contents\">&emsp;&emsp;</a> <a id=\"right_arrow\" href=\"S:ἐλεύθερος\">&ensp;&ensp;&ensp;&ensp;</a> </center> "}]}