{"word":"δουκηνάριος","slug":"δουκηνάριος","sections":[{"paragraph":""},{"paragraph":""},{"paragraph":"<entryFree id=\"n28148\" key=\"doukhna/rios\" type=\"main\" opt=\"n\" TEIform=\"entryFree\"> <orth extent=\"full\" lang=\"greek\" opt=\"n\" TEIform=\"orth\">δουκηνάριος</orth>, <gen lang=\"greek\" opt=\"n\" TEIform=\"gen\">ὁ</gen>, <abbr TEIform=\"abbr\">=</abbr> Lat. <sense id=\"n28148.0\" n=\"A\" level=\"1\" opt=\"n\" TEIform=\"sense\"> <tr_ opt=\"n\" TEIform=\"tr\">ducenarius, official receiving salary of</tr_> <bibl n=\"urn:cts:greekLit:tlg0563.tlg001:200\" default=\"NO\" TEIform=\"bibl\"> <biblScope TEIform=\"biblScope\">200</biblScope></bibl>,<bibl n=\"urn:cts:greekLit:tlg0563.tlg001:000\" default=\"NO\" TEIform=\"bibl\"> <biblScope TEIform=\"biblScope\">000</biblScope> </bibl> <tr_ opt=\"n\" TEIform=\"tr\">sesterces,</tr_> <bibl default=\"NO\" TEIform=\"bibl\"> <author TEIform=\"author\"><a class=\"S\" href=\"S:LSJ IG\">IG</a></author> <biblScope TEIform=\"biblScope\">14.1347</biblScope></bibl>, <bibl n=\"Perseus:abo:pap,P.Oxy.:1711:4\" default=\"NO\" TEIform=\"bibl\"> <title_ TEIform=\"title\"><a class=\"S\" href=\"S:LSJ POxy.\">POxy.</a></title_> <biblScope TEIform=\"biblScope\">1711.4</biblScope> </bibl> <date TEIform=\"date\">(iii A. D.)</date>, etc. </sense> <sense n=\"II\" id=\"n28148.1\" level=\"2\" opt=\"n\" TEIform=\"sense\"> fem. <orth extent=\"full\" lang=\"greek\" opt=\"n\" TEIform=\"orth\">δουκηναρία</orth>, <gen lang=\"greek\" opt=\"n\" TEIform=\"gen\">ἡ</gen>, <tr_ opt=\"n\" TEIform=\"tr\">assessment of</tr_> <bibl n=\"http://www.trismegistos.org/text/35951\" default=\"NO\" TEIform=\"bibl\"> <biblScope TEIform=\"biblScope\">200</biblScope></bibl>,<bibl n=\"Perseus:abo:pap,P.Oxy.:000\" default=\"NO\" TEIform=\"bibl\"> <biblScope TEIform=\"biblScope\">000</biblScope> </bibl> <tr_ opt=\"n\" TEIform=\"tr\">sesterces,</tr_> ib.<bibl n=\"Perseus:abo:pap,P.Oxy.:1274:14\" default=\"NO\" TEIform=\"bibl\"> <biblScope TEIform=\"biblScope\">1274.14</biblScope> </bibl> <date TEIform=\"date\">(iii A. D.)</date>.</sense> </entryFree>"}]}