{"word":"κατώρροπος","slug":"κατώρροπος","sections":[{"paragraph":""},{"paragraph":""},{"paragraph":"<entryFree id=\"n56176\" key=\"katw/rropos\" type=\"main\" opt=\"n\" TEIform=\"entryFree\"> <orth extent=\"full\" lang=\"greek\" opt=\"n\" TEIform=\"orth\">κατώρροπος</orth>, <itype lang=\"greek\" opt=\"n\" TEIform=\"itype\">ον</itype>, <sense id=\"n56176.0\" n=\"A\" level=\"1\" opt=\"n\" TEIform=\"sense\"> <xr opt=\"n\" TEIform=\"xr\"> <lbl opt=\"n\" TEIform=\"lbl\">=</lbl> <ref targOrder=\"U\" lang=\"greek\" TEIform=\"ref\">κατάρροπος</ref></xr>, <bibl n=\"urn:cts:greekLit:tlg4019.tlg006:p.244\" default=\"NO\" TEIform=\"bibl\"> <author TEIform=\"author\"><a class=\"S\" href=\"S:LSJ Olymp.\">Olymp.</a></author> <title_ TEIform=\"title\">in Phd.</title_> <biblScope TEIform=\"biblScope\">p.244</biblScope> </bibl> N.</sense> </entryFree>"}]}