{"word":"στυφαλμεῖν","slug":"στυφαλμεῖν","sections":[{"paragraph":""},{"paragraph":""},{"paragraph":"<entryFree id=\"n97423\" key=\"stufalmei=n\" type=\"gloss\" opt=\"n\" TEIform=\"entryFree\"> <orth extent=\"full\" lang=\"greek\" opt=\"n\" TEIform=\"orth\">στυφαλμεῖν·</orth> <foreign lang=\"greek\" TEIform=\"foreign\">σκυβαλίζειν</foreign>, <bibl default=\"NO\" TEIform=\"bibl\"> <author TEIform=\"author\"><a class=\"S\" href=\"S:LSJ Hsch.\">Hsch.</a></author> </bibl> <orth extent=\"full\" lang=\"greek\" opt=\"n\" TEIform=\"orth\">στυφᾶν·</orth> <foreign lang=\"greek\" TEIform=\"foreign\">βροντᾶν</foreign>, Id. <orth extent=\"full\" lang=\"greek\" opt=\"n\" TEIform=\"orth\">στυφεδανός</orth>, <gen lang=\"greek\" opt=\"n\" TEIform=\"gen\">ὁ</gen>, <sense id=\"n97423.0\" n=\"A\" level=\"1\" opt=\"n\" TEIform=\"sense\"> <xr opt=\"n\" TEIform=\"xr\"> <lbl opt=\"n\" TEIform=\"lbl\">v.</lbl> <ref targOrder=\"U\" lang=\"greek\" TEIform=\"ref\">τυφεδανός</ref></xr>.</sense> </entryFree>"}]}