{"word":"ἀμφιχορεύω","slug":"ἀμφιχορεύω","sections":[{"paragraph":""},{"paragraph":""},{"paragraph":"<entryFree id=\"n6139\" key=\"a)mfixoreu/w\" type=\"main\" opt=\"n\" TEIform=\"entryFree\"> <orth extent=\"full\" lang=\"greek\" opt=\"n\" TEIform=\"orth\">ἀμφιχορεύω</orth>, <sense id=\"n6139.0\" n=\"A\" level=\"1\" opt=\"n\" TEIform=\"sense\"> <tr_ opt=\"n\" TEIform=\"tr\">dance around,</tr_> abs., <bibl n=\"urn:cts:greekLit:tlg0319.tlg001:19\" default=\"NO\" TEIform=\"bibl\"> <author TEIform=\"author\"><a class=\"S\" href=\"S:LSJ Critias\">Critias</a></author> <biblScope TEIform=\"biblScope\">19</biblScope> </bibl> (anap.), <bibl default=\"NO\" TEIform=\"bibl\"> <title_ TEIform=\"title\">AP</title_> <biblScope TEIform=\"biblScope\">9.83</biblScope> </bibl> (<bibl default=\"NO\" TEIform=\"bibl\"> <author TEIform=\"author\"><a class=\"S\" href=\"S:LSJ Phil.\">Phil.</a></author> </bibl>): c. dat., <bibl n=\"urn:cts:greekLit:tlg0024.tlg001.perseus-grc1:1:27\" default=\"NO\" TEIform=\"bibl\"> <author TEIform=\"author\">Opp.</author> <title_ TEIform=\"title\">C.</title_> <biblScope TEIform=\"biblScope\">1.27</biblScope></bibl>.</sense> </entryFree>"}]}