{"word":"ἐπαΐσσω","slug":"ἐπαΐσσω","sections":[{"paragraph":""},{"paragraph":""},{"paragraph":"<entryFree id=\"n37895\" key=\"e)pai/+ssw\" type=\"main\" opt=\"n\" TEIform=\"entryFree\"> <orth extent=\"full\" lang=\"greek\" opt=\"n\" TEIform=\"orth\">ἐπαΐσσω</orth>, <gramGrp opt=\"n\" TEIform=\"gramGrp\"> <gram type=\"dialect\" opt=\"n\" TEIform=\"gram\"><a class=\"S\" href=\"S:LSJ Ep.\">Ep.</a></gram> </gramGrp> <tns opt=\"n\" TEIform=\"tns\"><a class=\"S\" href=\"S:LSJ aor.\">aor.</a></tns> <sense id=\"n37895.0\" n=\"A\" level=\"1\" opt=\"n\" TEIform=\"sense\"> <cit TEIform=\"cit\"> <quote_ lang=\"greek\" TEIform=\"quote\">ἐπήϊξα</quote_> <bibl n=\"urn:cts:greekLit:tlg0012.tlg002.perseus-grc1:10:322\" default=\"NO\" TEIform=\"bibl\"> <author TEIform=\"author\"><a class=\"S\" href=\"S:LSJ Od.\">Od.</a></author> <biblScope TEIform=\"biblScope\">10.322</biblScope></bibl></cit>, Iterat. <cit TEIform=\"cit\"> <quote_ lang=\"greek\" TEIform=\"quote\">ἐπαϊξασκε</quote_> <bibl n=\"urn:cts:greekLit:tlg0012.tlg001.perseus-grc1:17:462\" default=\"NO\" TEIform=\"bibl\"> <author TEIform=\"author\"><a class=\"S\" href=\"S:LSJ Il.\">Il.</a></author> <biblScope TEIform=\"biblScope\">17.462</biblScope> </bibl> </cit>: <gramGrp opt=\"n\" TEIform=\"gramGrp\"> <gram type=\"var\" opt=\"n\" TEIform=\"gram\"><a class=\"S\" href=\"S:LSJ contr.\">contr.</a></gram> </gramGrp> <orth extent=\"full\" lang=\"greek\" opt=\"n\" TEIform=\"orth\">ἐπᾴσσω</orth>, <gramGrp opt=\"n\" TEIform=\"gramGrp\"> <gram type=\"dialect\" opt=\"n\" TEIform=\"gram\"><a class=\"S\" href=\"S:LSJ Att.\">Att.</a></gram> </gramGrp> <orth extent=\"suff\" lang=\"greek\" opt=\"n\" TEIform=\"orth\">ἐπαίσθ-ττω</orth>, <tns opt=\"n\" TEIform=\"tns\"><a class=\"S\" href=\"S:LSJ fut.\">fut.</a></tns> <foreign lang=\"greek\" TEIform=\"foreign\">-ᾴξω</foreign>:—<tr_ opt=\"n\" TEIform=\"tr\">rush at</tr_> or <tr_ opt=\"n\" TEIform=\"tr\">upon</tr_>: c. gen. (never in <bibl default=\"NO\" TEIform=\"bibl\"> <author TEIform=\"author\"><a class=\"S\" href=\"S:LSJ Od.\">Od.</a></author> </bibl>), <foreign lang=\"greek\" TEIform=\"foreign\">ἵππων ἐπαϊξαι</foreign> <tr_ opt=\"n\" TEIform=\"tr\">rush at</tr_> them, <bibl n=\"urn:cts:greekLit:tlg0012.tlg001.perseus-grc1:5:263\" default=\"NO\" TEIform=\"bibl\"> <author TEIform=\"author\"><a class=\"S\" href=\"S:LSJ Il.\">Il.</a></author> <biblScope TEIform=\"biblScope\">5.263</biblScope> </bibl>; <cit TEIform=\"cit\"> <quote_ lang=\"greek\" TEIform=\"quote\">νεῶν</quote_> <bibl n=\"urn:cts:greekLit:tlg0012.tlg001.perseus-grc1:13:687\" default=\"NO\" TEIform=\"bibl\"> <biblScope TEIform=\"biblScope\">13.687</biblScope></bibl></cit>. </sense> <sense n=\"2\" id=\"n37895.1\" level=\"3\" opt=\"n\" TEIform=\"sense\"> c. dat. pers., <foreign lang=\"greek\" TEIform=\"foreign\">Κίρκῃ ἐπαΐξαι</foreign> <tr_ opt=\"n\" TEIform=\"tr\">rush upon</tr_> her, <bibl n=\"urn:cts:greekLit:tlg0012.tlg002.perseus-grc1:10:295\" default=\"NO\" TEIform=\"bibl\"> <author TEIform=\"author\"><a class=\"S\" href=\"S:LSJ Od.\">Od.</a></author> <biblScope TEIform=\"biblScope\">10.295</biblScope> </bibl>: in <bibl default=\"NO\" TEIform=\"bibl\"> <author TEIform=\"author\"><a class=\"S\" href=\"S:LSJ Il.\">Il.</a></author> </bibl> only c. dat. instrum., <foreign lang=\"greek\" TEIform=\"foreign\">ξίφει, δουρὶ ἐ.,</foreign> <bibl n=\"urn:cts:greekLit:tlg0012.tlg001.perseus-grc1:5:584\" default=\"NO\" TEIform=\"bibl\"> <biblScope TEIform=\"biblScope\">5.584</biblScope></bibl>, <bibl n=\"urn:cts:greekLit:tlg0012.tlg001.perseus-grc1:10:369\" default=\"NO\" TEIform=\"bibl\"> <biblScope TEIform=\"biblScope\">10.369</biblScope></bibl>, etc.; so <cit TEIform=\"cit\"> <quote_ lang=\"greek\" TEIform=\"quote\">μοι . . ἐπήϊσσον μελίῃσιν</quote_> <bibl n=\"urn:cts:greekLit:tlg0012.tlg002.perseus-grc1:14:281\" default=\"NO\" TEIform=\"bibl\"> <author TEIform=\"author\"><a class=\"S\" href=\"S:LSJ Od.\">Od.</a></author> <biblScope TEIform=\"biblScope\">14.281</biblScope></bibl></cit>. </sense> <sense n=\"3\" id=\"n37895.2\" level=\"3\" opt=\"n\" TEIform=\"sense\"> c. acc., <tr_ opt=\"n\" TEIform=\"tr\">assail, assault,</tr_> <cit TEIform=\"cit\"> <quote_ lang=\"greek\" TEIform=\"quote\">Ἕκτορα</quote_> <bibl n=\"urn:cts:greekLit:tlg0012.tlg001.perseus-grc1:23:64\" default=\"NO\" TEIform=\"bibl\"> <author TEIform=\"author\"><a class=\"S\" href=\"S:LSJ Il.\">Il.</a></author> <biblScope TEIform=\"biblScope\">23.64</biblScope> </bibl> </cit>; <cit TEIform=\"cit\"> <quote_ lang=\"greek\" TEIform=\"quote\">τεῖχος</quote_> <bibl n=\"urn:cts:greekLit:tlg0012.tlg001.perseus-grc1:12:308\" default=\"NO\" TEIform=\"bibl\"> <biblScope TEIform=\"biblScope\">12.308</biblScope> </bibl> </cit> (never so in <bibl default=\"NO\" TEIform=\"bibl\"> <author TEIform=\"author\"><a class=\"S\" href=\"S:LSJ Od.\">Od.</a></author> </bibl>):—<gramGrp opt=\"n\" TEIform=\"gramGrp\"> <gram type=\"voice\" opt=\"n\" TEIform=\"gram\"><a class=\"S\" href=\"S:LSJ Med.\">Med.</a></gram></gramGrp>, <foreign lang=\"greek\" TEIform=\"foreign\">ἐπαϊξασθαι ἄεθλον</foreign> <tr_ opt=\"n\" TEIform=\"tr\">rush at</tr_> (i.e. <tr_ opt=\"n\" TEIform=\"tr\">seize upon</tr_>) the prize, <bibl n=\"urn:cts:greekLit:tlg0012.tlg001.perseus-grc1:23:773\" default=\"NO\" TEIform=\"bibl\"> <author TEIform=\"author\"><a class=\"S\" href=\"S:LSJ Il.\">Il.</a></author> <biblScope TEIform=\"biblScope\">23.773</biblScope></bibl>. </sense> <sense n=\"4\" id=\"n37895.3\" level=\"3\" opt=\"n\" TEIform=\"sense\"> abs. (so usu. in <bibl default=\"NO\" TEIform=\"bibl\"> <author TEIform=\"author\">Hom.</author> </bibl>), of a hawk, <foreign lang=\"greek\" TEIform=\"foreign\">ταρφέ) ἐπαϊσσει</foreign> <tr_ opt=\"n\" TEIform=\"tr\">makes</tr_> frequent <tr_ opt=\"n\" TEIform=\"tr\">swoops,</tr_> <bibl n=\"urn:cts:greekLit:tlg0013.tlg001.perseus-grc1:22:142\" default=\"NO\" TEIform=\"bibl\"> <biblScope TEIform=\"biblScope\">22.142</biblScope> </bibl>; of the wind, <cit TEIform=\"cit\"> <quote_ lang=\"greek\" TEIform=\"quote\">ἐπαΐξας . . ἐκ νεφελάων</quote_> <bibl n=\"urn:cts:greekLit:tlg0013.tlg001.perseus-grc1:2:146\" default=\"NO\" TEIform=\"bibl\"> <biblScope TEIform=\"biblScope\">2.146</biblScope></bibl></cit>, etc.; <cit TEIform=\"cit\"> <quote_ lang=\"greek\" TEIform=\"quote\">σῦς ἐπαΐσσων βίᾳ</quote_> <bibl n=\"urn:cts:greekLit:tlg0199.tlg001:5:116\" default=\"NO\" TEIform=\"bibl\"> <author TEIform=\"author\"><a class=\"S\" href=\"S:LSJ B.\">B.</a></author> <biblScope TEIform=\"biblScope\">5.116</biblScope></bibl></cit>, cf. <bibl n=\"urn:cts:greekLit:tlg0019.tlg001.perseus-grc1:1171\" default=\"NO\" TEIform=\"bibl\"> <author TEIform=\"author\"><a class=\"S\" href=\"S:LSJ Ar.\">Ar.</a></author> <title_ TEIform=\"title\"><a class=\"S\" href=\"S:LSJ Ach.\">Ach.</a></title_> <biblScope TEIform=\"biblScope\">1171</biblScope> </bibl> (lyr.); <cit TEIform=\"cit\"> <quote_ lang=\"greek\" TEIform=\"quote\">ἐπᾴξας ἐς δόμους</quote_> <bibl n=\"urn:cts:greekLit:tlg0011.tlg003.perseus-grc1:305\" default=\"NO\" TEIform=\"bibl\"> <author TEIform=\"author\"><a class=\"S\" href=\"S:LSJ S.\">S.</a></author> <title_ TEIform=\"title\"><a class=\"S\" href=\"S:LSJ Aj.\">Aj.</a></title_> <biblScope TEIform=\"biblScope\">305</biblScope> </bibl> </cit>; rare in Prose, as <bibl n=\"urn:cts:greekLit:tlg0059.tlg006.perseus-grc1:190a\" default=\"NO\" TEIform=\"bibl\"> <author TEIform=\"author\"><a class=\"S\" href=\"S:LSJ Pl.\">Pl.</a></author> <title_ TEIform=\"title\"><a class=\"S\" href=\"S:LSJ Tht.\">Tht.</a></title_> <biblScope TEIform=\"biblScope\">190a</biblScope> </bibl> (metaph.), <bibl n=\"urn:cts:greekLit:tlg0086.tlg014:629b:25\" default=\"NO\" TEIform=\"bibl\"> <author TEIform=\"author\"><a class=\"S\" href=\"S:LSJ Arist.\">Arist.</a></author> <title_ TEIform=\"title\"><a class=\"S\" href=\"S:LSJ HA\">HA</a></title_> <biblScope TEIform=\"biblScope\">629b25</biblScope> </bibl>:—also <gramGrp opt=\"n\" TEIform=\"gramGrp\"> <gram type=\"voice\" opt=\"n\" TEIform=\"gram\"><a class=\"S\" href=\"S:LSJ Med.\">Med.</a></gram></gramGrp>, <cit TEIform=\"cit\"> <quote_ lang=\"greek\" TEIform=\"quote\">χειμῶνος μέλλοντος ἐπαΐσσεσθαι ὁδοῖο</quote_> <bibl n=\"urn:cts:greekLit:tlg0653.tlg001.perseus-grc1:1139\" default=\"NO\" TEIform=\"bibl\"> <author TEIform=\"author\"><a class=\"S\" href=\"S:LSJ Arat.\">Arat.</a></author> <biblScope TEIform=\"biblScope\">1139</biblScope></bibl></cit>. </sense> <sense n=\"5\" id=\"n37895.4\" level=\"3\" opt=\"n\" TEIform=\"sense\"> <foreign lang=\"greek\" TEIform=\"foreign\">τὰ νεῦρα ἐπαΐσσεται ἀμφὶ τὰς φύσιας τῶν ἄρθρων</foreign> (in the development of the embryo), dub. in <bibl n=\"urn:cts:greekLit:tlg0627.tlg024:17\" default=\"NO\" TEIform=\"bibl\"> <author TEIform=\"author\"><a class=\"S\" href=\"S:LSJ Hp.\">Hp.</a></author> <title_ TEIform=\"title\"><a class=\"S\" href=\"S:LSJ Nat.Puer.\">Nat.Puer.</a></title_> <biblScope TEIform=\"biblScope\">17</biblScope></bibl>. </sense> <sense n=\"II\" id=\"n37895.5\" level=\"2\" opt=\"n\" TEIform=\"sense\"> later, with acc. of the Instrument of motion, <foreign lang=\"greek\" TEIform=\"foreign\">ἐ. πόδα</foreign> <tr_ opt=\"n\" TEIform=\"tr\">move with hasty</tr_> step, <bibl n=\"urn:cts:greekLit:tlg0006.tlg007.perseus-grc1:1071\" default=\"NO\" TEIform=\"bibl\"> <author TEIform=\"author\"><a class=\"S\" href=\"S:LSJ E.\">E.</a></author> <title_ TEIform=\"title\"><a class=\"S\" href=\"S:LSJ Hec.\">Hec.</a></title_> <biblScope TEIform=\"biblScope\">1071</biblScope> </bibl> (lyr.); <cit TEIform=\"cit\"> <quote_ lang=\"greek\" TEIform=\"quote\">ἐ. ξίφος</quote_> <bibl n=\"urn:cts:greekLit:tlg0001.tlg001.perseus-grc1:1:1254\" default=\"NO\" TEIform=\"bibl\"> <author TEIform=\"author\"><a class=\"S\" href=\"S:LSJ A.R.\">A.R.</a></author> <biblScope TEIform=\"biblScope\">1.1254</biblScope> </bibl> </cit>: —<gramGrp opt=\"n\" TEIform=\"gramGrp\"> <gram type=\"voice\" opt=\"n\" TEIform=\"gram\"><a class=\"S\" href=\"S:LSJ Pass.\">Pass.</a></gram> </gramGrp> even in <bibl default=\"NO\" TEIform=\"bibl\"> <author TEIform=\"author\">Hom.</author></bibl>, <foreign lang=\"greek\" TEIform=\"foreign\">χεῖρες ὤμων ἀμφοτέρωθεν ἐπαΐσσονται ἐλαφραί</foreign> they <tr_ opt=\"n\" TEIform=\"tr\">move lightly,</tr_> <bibl n=\"urn:cts:greekLit:tlg0012.tlg001.perseus-grc1:23:628\" default=\"NO\" TEIform=\"bibl\"> <author TEIform=\"author\"><a class=\"S\" href=\"S:LSJ Il.\">Il.</a></author> <biblScope TEIform=\"biblScope\">23.628</biblScope> </bibl> (<xr opt=\"n\" TEIform=\"xr\"> <lbl opt=\"n\" TEIform=\"lbl\">v.l.</lbl> <ref targOrder=\"U\" lang=\"greek\" TEIform=\"ref\">ἀπ-</ref> </xr>)<foreign lang=\"greek\" TEIform=\"foreign\">. [ᾱ-</foreign> <gramGrp opt=\"n\" TEIform=\"gramGrp\"> <gram type=\"dialect\" opt=\"n\" TEIform=\"gram\"><a class=\"S\" href=\"S:LSJ Ep.\">Ep.</a></gram></gramGrp>, <foreign lang=\"greek\" TEIform=\"foreign\">ᾰ-</foreign> <gramGrp opt=\"n\" TEIform=\"gramGrp\"> <gram type=\"dialect\" opt=\"n\" TEIform=\"gram\"><a class=\"S\" href=\"S:LSJ Att.\">Att.</a></gram> </gramGrp>]</sense> </entryFree>"}]}